kbib/__init__.py
kbib/parseRefs.py
kbib/utils.py
kbib-0.2.0.dist-info/LICENSE
kbib-0.2.0.dist-info/METADATA
kbib-0.2.0.dist-info/WHEEL
kbib-0.2.0.dist-info/entry_points.txt
kbib-0.2.0.dist-info/top_level.txt
kbib-0.2.0.dist-info/zip-safe
kbib-0.2.0.dist-info/RECORD
