Metadata-Version: 2.1
Name: kbib
Version: 0.2.0
Summary: A command line tool to get bibtex information from DOIs and PDFs
Author: Koushik Naskar
Author-email: koushik.naskar9@gmail.com
License: MIT
Project-URL: Source Code, https://github.com/Koushikphy/kbib
Keywords: bibtex references doi crossref
Classifier: Development Status :: 5 - Production/Stable
Classifier: Environment :: Console
Classifier: Intended Audience :: Science/Research
Classifier: Natural Language :: English
Classifier: License :: OSI Approved :: MIT License
Classifier: Operating System :: OS Independent
Classifier: Programming Language :: Python :: Implementation :: CPython
Classifier: Programming Language :: Python :: 3.6
Classifier: Topic :: System :: Shells
Requires-Python: >=3.6
License-File: LICENSE
Requires-Dist: bibtexparser >=1.4.0
Requires-Dist: rich >=12.6.0
Requires-Dist: jellyfish >=1.1.0
Requires-Dist: requests-cache
Provides-Extra: pdf
Requires-Dist: pdf2doi ; extra == 'pdf'
